{"is_source_file": false, "format": "", "description": "", "external_files": [], "external_methods": [], "published": [], "classes": [], "methods": [], "calls": [], "search-terms": [], "state": 2, "file_id": 10, "knowledge_revision": 23, "git_revision": "61b1e80a610321c6dce632159d06a5884343bca0", "hash": "45e13bfa46a2f4dc77cf3e3f1e8b40f7", "format-version": 4, "code-base-name": "mongo_database", "filename": "mongo_database/README.md", "revision_history": [{"23": "61b1e80a610321c6dce632159d06a5884343bca0"}]}